matchmatrix/__init__.py
matchmatrix/constants.py
matchmatrix/functions.py
matchmatrix/manager.py
matchmatrix-2.0.2.dist-info/LICENSE
matchmatrix-2.0.2.dist-info/METADATA
matchmatrix-2.0.2.dist-info/WHEEL
matchmatrix-2.0.2.dist-info/top_level.txt
matchmatrix-2.0.2.dist-info/RECORD
