Metadata-Version: 2.1
Name: matchmatrix
Version: 2.0.2
Summary: Customisable class to produce a matrix of match scores across multiple dimensions
Home-page: https://github.com/porteverte/matchmatrix
Author: Porte Verte
Author-email: Port Verte <porte_verte@outlook.com>
Project-URL: Homepage, https://github.com/porteverte/matchmatrix
Project-URL: Issues, https://github.com/porteverte/matchmatrix/issues
Classifier: Programming Language :: Python :: 3
Classifier: License :: OSI Approved :: MIT License
Classifier: Operating System :: OS Independent
Requires-Python: >=3.8
License-File: LICENSE
